indexify/cli/__init__.py
indexify/cli/build_images.py
indexify/cli/deploy.py
indexify/cli/executor.py
indexify/executor/README.md
indexify/executor/blob_store/__init__.py
indexify/executor/blob_store/blob_metadata.py
indexify/executor/blob_store/blob_store.py
indexify/executor/blob_store/local_fs_blob_store.py
indexify/executor/blob_store/metrics/blob_store.py
indexify/executor/blob_store/s3_blob_store.py
indexify/executor/channel_manager.py
indexify/executor/cloud_events.py
indexify/executor/executor.py
indexify/executor/function_allowlist.py
indexify/executor/function_executor/function_executor.py
indexify/executor/function_executor/health_checker.py
indexify/executor/function_executor/metrics/function_executor.py
indexify/executor/function_executor/metrics/health_checker.py
indexify/executor/function_executor/server/client_configuration.py
indexify/executor/function_executor/server/function_executor_server.py
indexify/executor/function_executor/server/function_executor_server_factory.py
indexify/executor/function_executor/server/subprocess_function_executor_server.py
indexify/executor/function_executor/server/subprocess_function_executor_server_factory.py
indexify/executor/function_executor_controller/__init__.py
indexify/executor/function_executor_controller/aio_utils.py
indexify/executor/function_executor_controller/allocation_info.py
indexify/executor/function_executor_controller/allocation_input.py
indexify/executor/function_executor_controller/allocation_output.py
indexify/executor/function_executor_controller/allocation_runner.py
indexify/executor/function_executor_controller/blob_utils.py
indexify/executor/function_executor_controller/completed_allocation_metrics.py
indexify/executor/function_executor_controller/create_function_executor.py
indexify/executor/function_executor_controller/debug_event_loop.py
indexify/executor/function_executor_controller/downloads.py
indexify/executor/function_executor_controller/events.py
indexify-0.4.55.dist-info/METADATA
indexify-0.4.55.dist-info/WHEEL
indexify-0.4.55.dist-info/entry_points.txt
indexify-0.4.55.dist-info/RECORD
